pptx2txt2/__init__.py
pptx2txt2/py.typed
pptx2txt2-1.1.0.dist-info/LICENSE.txt
pptx2txt2-1.1.0.dist-info/METADATA
pptx2txt2-1.1.0.dist-info/WHEEL
pptx2txt2-1.1.0.dist-info/top_level.txt
pptx2txt2-1.1.0.dist-info/RECORD
